catkin_sphinx/ShLexer.py
catkin_sphinx/__init__.py
catkin_sphinx/cmake.py
catkin_sphinx/theme/ros-theme/theme.conf
catkin_sphinx/theme/ros-theme/static/pygments.css
catkin_sphinx/theme/ros-theme/static/sphinxdoc.css
catkin_sphinx-0.3.2.dist-info/METADATA
catkin_sphinx-0.3.2.dist-info/WHEEL
catkin_sphinx-0.3.2.dist-info/top_level.txt
catkin_sphinx-0.3.2.dist-info/RECORD
