Metadata-Version: 2.1
Name: catkin-sphinx
Version: 0.3.2
Summary: Sphinx extension for Catkin projects
Home-page: http://www.ros.org/
Author: William Woodall
Author-email: william@osrfoundation.org
License: BSD
Download-URL: http://pr.willowgarage.com/downloads/catkin_sphinx/
Keywords: ROS
Platform: UNKNOWN
Classifier: Programming Language :: Python
Classifier: License :: OSI Approved :: BSD License
